app_min.py
nano_base-0.1.0.dist-info/licenses/LICENSE
nano_base-0.1.0.dist-info/METADATA
nano_base-0.1.0.dist-info/WHEEL
nano_base-0.1.0.dist-info/entry_points.txt
nano_base-0.1.0.dist-info/top_level.txt
nano_base-0.1.0.dist-info/RECORD
