Metadata-Version: 2.4
Name: nano-base
Version: 0.1.0
Summary: Tiny base converter (2..36) in ~1KB (zero deps).
Author: ozgunlu
License: MIT
Project-URL: Homepage, https://github.com/ozgunlu/nano-base
Project-URL: Issues, https://github.com/ozgunlu/nano-base/issues
Requires-Python: >=3.8
License-File: LICENSE
Dynamic: license-file
